setup.py
dockerns/__init__.py
dockerns/cli.py
dockerns/discovery.py
dockerns/dnsserver.py
dockerns.egg-info/PKG-INFO
dockerns.egg-info/SOURCES.txt
dockerns.egg-info/dependency_links.txt
dockerns.egg-info/entry_points.txt
dockerns.egg-info/requires.txt
dockerns.egg-info/top_level.txt
dockerns.egg-info/zip-safe