Metadata-Version: 1.0
Name: dockerns
Version: 0.0.2
Summary: Docker Service DNS Server
Home-page: https://github.com/jamescun/dockerns
Author: James Cunningham
Author-email: tetrauk@gmail.com
License: MIT
Platform: UNKNOWN
Classifier: Environment :: Console
Classifier: Intended Audience :: Developers
Classifier: Intended Audience :: System Administrators
Classifier: License :: OSI Approved :: MIT License
Classifier: Topic :: Internet :: Name Service (DNS)
